wagtail_tabbed_structblock/README.md
wagtail_tabbed_structblock/__init__.py
wagtail_tabbed_structblock/apps.py
wagtail_tabbed_structblock/blocks.py
wagtail_tabbed_structblock/migrations/__init__.py
wagtail_tabbed_structblock/poetry.lock
wagtail_tabbed_structblock/pyproject.toml
wagtail_tabbed_structblock/setup.py
wagtail_tabbed_structblock/static/wagtail_tabbed_structblock/css/tabbed_structblock.css
wagtail_tabbed_structblock/static/wagtail_tabbed_structblock/js/tabbed_structblock.js
wagtail_tabbed_structblock/templates/wagtail_tabbed_structblock/tabbed_struct_block.html
wagtail_tabbed_structblock/tests.py
wagtail_tabbed_structblock-0.0.8.dist-info/METADATA
wagtail_tabbed_structblock-0.0.8.dist-info/WHEEL
wagtail_tabbed_structblock-0.0.8.dist-info/RECORD
