Metadata-Version: 2.1
Name: wagtail-tabbed-structblock
Version: 0.0.8
Summary: 
Author: Eric Kersten
Author-email: eric.kersten@egodesign.io
Requires-Python: >=3.10,<4.0
Classifier: Programming Language :: Python :: 3
Classifier: Programming Language :: Python :: 3.10
Classifier: Programming Language :: Python :: 3.11
Classifier: Programming Language :: Python :: 3.12
